twtvt/__init__.py
twtvt/__main__.py
twtvt/cli/__init__.py
twtvt/cli/commands.py
twtvt/main.py
twtvt/tests/__init__.py
twtvt/tests/sample_test.py
twtvt/utils/__init__.py
twtvt/utils/cookie_parser.py
twtvt/utils/download_video.py
twtvt/utils/execute_parallel.py
twtvt/utils/istarmap.py
twtvt/utils/logger.py
twtvt/utils/monsnode_parser.py
twtvt/utils/twitter_parser.py
twtvt/utils/uri_validator.py
twtvt-2023.10.15.dist-info/METADATA
twtvt-2023.10.15.dist-info/WHEEL
twtvt-2023.10.15.dist-info/entry_points.txt
twtvt-2023.10.15.dist-info/RECORD
