Metadata-Version: 2.1
Name: twtvt
Version: 2023.10.15
Summary: 
Requires-Python: >=3.9,<4.0
Classifier: Programming Language :: Python :: 3
Classifier: Programming Language :: Python :: 3.9
Classifier: Programming Language :: Python :: 3.10
Classifier: Programming Language :: Python :: 3.11
Requires-Dist: beautifulsoup4 (>=4.12.2,<5.0.0)
Requires-Dist: browser-cookie3 (>=0.19.1,<0.20.0)
Requires-Dist: httpx (>=0.24.0,<0.25.0)
Requires-Dist: playwright (>=1.32.1,<2.0.0)
Requires-Dist: poetry (>=1.4.0,<2.0.0)
Requires-Dist: rich (>=13.3.4,<14.0.0)
Requires-Dist: tenacity (>=8.2.2,<9.0.0)
Requires-Dist: typer (>=0.7.0,<0.8.0)
Requires-Dist: yt-dlp (>=2023.3.4,<2024.0.0)
